dev_handlers/__init__.py
dev_handlers/start.py
telekit/__init__.py
telekit/callback_query_handler.py
telekit/chain.py
telekit/chain_base.py
telekit/chain_entry_logic.py
telekit/chain_inline_keyboards_logic.py
telekit/handler.py
telekit/init.py
telekit/input_handler.py
telekit/logger.py
telekit/on.py
telekit/parameters.py
telekit/senders.py
telekit/server.py
telekit/styles.py
telekit/timeout.py
telekit/tools.py
telekit/user.py
telekit/buildtext/__init__.py
telekit/buildtext/formatter.py
telekit/buildtext/styles.py
telekit/chapters/__init__.py
telekit/chapters/chapters.py
telekit/example/__init__.py
telekit/example/example_server.py
telekit/example/example_handlers/__init__.py
telekit/example/example_handlers/counter.py
telekit/example/example_handlers/entry.py
telekit/example/example_handlers/faq.py
telekit/example/example_handlers/on_text.py
telekit/example/example_handlers/pages.py
telekit/example/example_handlers/start.py
telekit/snapvault/__init__.py
telekit/snapvault/snapcode.py
telekit/snapvault/snapvault.py
telekit/telekit_dsl/__init__.py
telekit/telekit_dsl/mixin.py
telekit/telekit_dsl/telekit_dsl.py
telekit/telekit_dsl/telekit_orm.py
telekit/telekit_dsl/parser/__init__.py
telekit/telekit_dsl/parser/builder.py
telekit/telekit_dsl/parser/lexer.py
telekit/telekit_dsl/parser/nodes.py
telekit/telekit_dsl/parser/parser.py
telekit/telekit_dsl/parser/token.py
telekit-1.3.0.dist-info/licenses/LICENSE
telekit-1.3.0.dist-info/METADATA
telekit-1.3.0.dist-info/WHEEL
telekit-1.3.0.dist-info/top_level.txt
telekit-1.3.0.dist-info/RECORD
