Metadata-Version: 2.4
Name: telekit
Version: 1.3.0
Summary: Declarative, developer-friendly library for building Telegram bots
Home-page: https://github.com/Romashkaa/telekit
Author: romashka
Author-email: notromashka@gmail.com
License: MIT
Project-URL: GitHub, https://github.com/Romashkaa/telekit
Project-URL: Telegram, https://t.me/TelekitLib
Keywords: files speedfiles
Classifier: Programming Language :: Python :: 3.13
Classifier: Programming Language :: Python :: 3.14
Classifier: License :: OSI Approved :: MIT License
Classifier: Operating System :: OS Independent
Requires-Python: >=3.13.7
License-File: LICENSE
Requires-Dist: pyTelegramBotAPI>=4.29.1
Requires-Dist: charset_normalizer>=3.4.2
Dynamic: author
Dynamic: author-email
Dynamic: classifier
Dynamic: description
Dynamic: description-content-type
Dynamic: home-page
Dynamic: keywords
Dynamic: license-file
Dynamic: project-url
Dynamic: requires-dist
Dynamic: requires-python
Dynamic: summary
